[
  {
    "title": "[AL] Teste",
    "start": "2022-10-31 00:00",
    "end": "2022-10-31 23:59",
    "groupId": 1,
    "filterId": 111
  },
  {
    "title": "[AL] Teste",
    "start": "2023-01-04 00:00",
    "end": "2023-01-04 23:59",
    "groupId": 1,
    "filterId": 111
  },
  {
    "title": "[AL] Recurso",
    "start": "2023-01-25 00:00",
    "end": "2023-01-25 23:59",
    "groupId": 1,
    "filterId": 111
  },
  {
    "title": "[Cálculo] Teste",
    "start": "2022-11-02 00:00",
    "end": "2022-11-02 23:59",
    "groupId": 1,
    "filterId": 112
  },
  {
    "title": "[Cálculo] Teste",
    "start": "2023-01-06 00:00",
    "end": "2023-01-06 23:59",
    "groupId": 1,
    "filterId": 112
  },
  {
    "title": "[Cálculo] Recurso",
    "start": "2023-02-03 00:00",
    "end": "2023-02-03 23:59",
    "groupId": 1,
    "filterId": 112
  },
  {
    "title": "[Cálculo] Recurso",
    "start": "2023-02-03 00:00",
    "end": "2023-02-03 23:59",
    "groupId": 1,
    "filterId": 112
  },
  {
    "title": "[LI1] Entrega TP",
    "start": "2022-11-12 00:00",
    "end": "2022-11-12 23:59",
    "groupId": 1,
    "filterId": 113
  },
  {
    "title": "[LI1] Entrega TP",
    "start": "2023-01-02 00:00",
    "end": "2022-01-02 23:59",
    "groupId": 1,
    "filterId": 113
  },
  {
    "title": "[PF] Teste 50 Questões",
    "start": "2022-11-03 00:00",
    "end": "2022-11-03 23:59",
    "groupId": 1,
    "filterId": 114
  },
  {
    "title": "[PF] Teste Final",
    "start": "2023-01-09 00:00",
    "end": "2023-01-09 23:59",
    "groupId": 1,
    "filterId": 114
  },
  {
    "title": "[PF] Recurso",
    "start": "2023-01-30 00:00",
    "end": "2023-01-30 23:59",
    "groupId": 1,
    "filterId": 114
  },
  {
    "title": "[TMD] Teste",
    "start": "2022-11-04 00:00",
    "end": "2022-11-04 23:59",
    "groupId": 1,
    "filterId": 115
  },
  {
    "title": "[TMD] Teste",
    "start": "2023-01-11 00:00",
    "end": "2023-01-11 23:59",
    "groupId": 1,
    "filterId": 115
  },
  {
    "title": "[TMD] Recurso",
    "start": "2023-02-01 00:00",
    "end": "2023-02-01 23:59",
    "groupId": 1,
    "filterId": 115
  },
  {
    "title": "[AlgC] Teste",
    "start": "2022-11-03 00:00",
    "end": "2022-11-03 23:59",
    "groupId": 2,
    "filterId": 211
  },
  {
    "title": "[AlgC] Teste",
    "start": "2023-01-10 00:00",
    "end": "2023-01-10 23:59",
    "groupId": 2,
    "filterId": 211
  },
  {
    "title": "[AlgC] Recurso",
    "start": "2023-02-04 00:00",
    "end": "2023-02-04 23:59",
    "groupId": 2,
    "filterId": 211
  },
  {
    "title": "[ArqC] Teste",
    "start": "2022-11-04 00:00",
    "end": "2022-11-04 23:59",
    "groupId": 2,
    "filterId": 212
  },
  {
    "title": "[ArqC] Teste",
    "start": "2023-01-03 00:00",
    "end": "2023-01-03 23:59",
    "groupId": 2,
    "filterId": 212
  },
  {
    "title": "[ArqC] Recurso",
    "start": "2023-01-26 00:00",
    "end": "2023-01-26 23:59",
    "groupId": 2,
    "filterId": 212
  },
  {
    "title": "[EA] Teste",
    "start": "2022-10-31 00:00",
    "end": "2022-10-31 23:59",
    "groupId": 2,
    "filterId": 213
  },
  {
    "title": "[EA] Teste",
    "start": "2023-01-12 00:00",
    "end": "2023-01-12 23:59",
    "groupId": 2,
    "filterId": 213
  },
  {
    "title": "[EA] Recurso",
    "start": "2023-02-02 00:00",
    "end": "2023-02-02 23:59",
    "groupId": 2,
    "filterId": 213
  },
  {
    "title": "[FM] Recurso",
    "start": "2023-01-24 00:00",
    "end": "2023-01-24 23:59",
    "groupId": 2,
    "filterId": 214
  },
  {
    "title": "[FCD] Teste",
    "start": "2022-11-02 00:00",
    "end": "2022-11-02 23:59",
    "groupId": 2,
    "filterId": 215
  },
  {
    "title": "[FCD] Teste",
    "start": "2023-01-05 00:00",
    "end": "2023-01-05 23:59",
    "groupId": 2,
    "filterId": 215
  },
  {
    "title": "[FCD] Recurso",
    "start": "2023-01-31 00:00",
    "end": "2023-01-31 23:59",
    "groupId": 2,
    "filterId": 215
  },
  {
    "title": "[CP] Entrega TP",
    "start": "2022-10-07 00:00",
    "end": "2022-10-07 23:59",
    "groupId": 3,
    "filterId": 311
  },
  {
    "title": "[CP] Entrega TP",
    "start": "2022-10-28 00:00",
    "end": "2022-10-28 23:59",
    "groupId": 3,
    "filterId": 311
  },
  {
    "title": "[CP] Entrega TP",
    "start": "2023-01-12 00:00",
    "end": "2023-01-12 23:59",
    "groupId": 3,
    "filterId": 311
  },
  {
    "title": "[CP] Teste",
    "start": "2023-01-03 00:00",
    "end": "2023-01-03 23:59",
    "groupId": 3,
    "filterId": 311
  },
  {
    "title": "[CP] Teste",
    "start": "2023-01-13 00:00",
    "end": "2023-01-13 23:59",
    "groupId": 3,
    "filterId": 311
  },
  {
    "title": "[CP] Teste",
    "start": "2023-01-24 00:00",
    "end": "2023-01-24 23:59",
    "groupId": 3,
    "filterId": 311
  },
  {
    "title": "[CC] Entrega TP",
    "start": "2023-01-02 00:00",
    "end": "2023-01-02 23:59",
    "groupId": 3,
    "filterId": 312
  },
  {
    "title": "[CC] Teste",
    "start": "2023-01-11 00:00",
    "end": "2023-01-11 23:59",
    "groupId": 3,
    "filterId": 312
  },
  {
    "title": "[CC] Recurso",
    "start": "2023-02-01 00:00",
    "end": "2023-02-01 23:59",
    "groupId": 3,
    "filterId": 312
  },
  {
    "title": "[DSS] Entrega TP",
    "start": "2022-10-20 00:00",
    "end": "2022-10-20 23:59",
    "groupId": 3,
    "filterId": 313
  },
  {
    "title": "[DSS] Entrega TP",
    "start": "2022-11-17 00:00",
    "end": "2022-11-17 23:59",
    "groupId": 3,
    "filterId": 313
  },
  {
    "title": "[DSS] Entrega TP",
    "start": "2023-01-07 00:00",
    "end": "2023-01-07 23:59",
    "groupId": 3,
    "filterId": 313
  },
  {
    "title": "[DSS] Teste",
    "start": "2023-01-06 00:00",
    "end": "2023-01-06 23:59",
    "groupId": 3,
    "filterId": 313
  },
  {
    "title": "[DSS] Recurso",
    "start": "2023-01-30 00:00",
    "end": "2023-01-30 23:59",
    "groupId": 3,
    "filterId": 313
  },
  {
    "title": "[IA] Entrega TP",
    "start": "2022-12-16 00:00",
    "end": "2022-12-16 23:59",
    "groupId": 3,
    "filterId": 314
  },
  {
    "title": "[IA] Teste",
    "start": "2023-01-04 00:00",
    "end": "2023-01-04 23:59",
    "groupId": 3,
    "filterId": 314
  },
  {
    "title": "[IA] Recurso",
    "start": "2023-01-25 00:00",
    "end": "2023-01-25 23:59",
    "groupId": 3,
    "filterId": 314
  },
  {
    "title": "[LI4] Entrega TP",
    "start": "2022-10-24 00:00",
    "end": "2022-10-24 23:59",
    "groupId": 3,
    "filterId": 315
  },
  {
    "title": "[LI4] Entrega TP",
    "start": "2022-11-28 00:00",
    "end": "2022-11-28 23:59",
    "groupId": 3,
    "filterId": 315
  },
  {
    "title": "[LI4] Entrega TP",
    "start": "2023-01-14 00:00",
    "end": "2023-01-14 23:59",
    "groupId": 3,
    "filterId": 315
  },
  {
    "title": "[SD] Entrega TP",
    "start": "2023-01-09 00:00",
    "end": "2023-01-09 23:59",
    "groupId": 3,
    "filterId": 316
  },
  {
    "title": "[SD] Teste",
    "start": "2023-01-02 00:00",
    "end": "2023-01-02 23:59",
    "groupId": 3,
    "filterId": 316
  },
  {
    "title": "[SD] Recurso",
    "start": "2023-01-23 00:00",
    "end": "2023-01-23 23:59",
    "groupId": 3,
    "filterId": 316
  },
  {}
]
